AUTHORS
LICENSE
MANIFEST.in
README.rst
setup.py
pinax/__init__.py
pinax/cms/__init__.py
pinax/cms/admin.py
pinax/cms/forms.py
pinax/cms/managers.py
pinax/cms/models.py
pinax/cms/urls.py
pinax/cms/views.py
pinax/cms/tests/__init__.py
pinax/cms/tests/models.py
pinax/cms/tests/tests.py
pinax/cms/tests/urls.py
pinax_cms.egg-info/PKG-INFO
pinax_cms.egg-info/SOURCES.txt
pinax_cms.egg-info/dependency_links.txt
pinax_cms.egg-info/not-zip-safe
pinax_cms.egg-info/requires.txt
pinax_cms.egg-info/top_level.txt